download_station_api/__init__.py
download_station_api/download_station_api.py
download_station_api/utils/__init__.py
download_station_api/utils/api_endpoint_details.py
download_station_api/utils/auth_error.py
download_station_api-0.1.2.dist-info/AUTHORS.rst
download_station_api-0.1.2.dist-info/LICENSE
download_station_api-0.1.2.dist-info/METADATA
download_station_api-0.1.2.dist-info/WHEEL
download_station_api-0.1.2.dist-info/top_level.txt
download_station_api-0.1.2.dist-info/RECORD
