Metadata-Version: 2.1
Name: download-station-api
Version: 0.1.2
Summary: Small python wrapper for interacting with the Synology Download Station
Home-page: https://github.com/paul-armstrong-dev/download_station_api
Author: Paul Armstrong
Author-email: paul_armstrong211@gmail.com
License: MIT license
Keywords: download_station_api,synology
Platform: UNKNOWN
Classifier: Development Status :: 2 - Pre-Alpha
Classifier: Intended Audience :: Developers
Classifier: License :: OSI Approved :: MIT License
Classifier: Natural Language :: English
Classifier: Programming Language :: Python :: 3
Classifier: Programming Language :: Python :: 3.6
Classifier: Programming Language :: Python :: 3.7
Classifier: Programming Language :: Python :: 3.8
Requires-Python: >=3.6
License-File: LICENSE
License-File: AUTHORS.rst
Requires-Dist: loguru (==0.5.3)
Requires-Dist: requests (==2.25.1)
